{
  "project_info": {
    "project_number": "456840650976",
    "project_id": "fillings-coulsdon-f12a1",
    "storage_bucket": "fillings-coulsdon-f12a1.firebasestorage.app"
  },
  "client": [
    {
      "client_info": {
        "mobilesdk_app_id": "1:456840650976:android:6238dd0fd34240b959f085",
        "android_client_info": {
          "package_name": "com.example.signuploginfirebase"
        }
      },
      "oauth_client": [],
      "api_key": [
        {
          "current_key": "AIzaSyCNy2DeD16nsaJGZvp4EEDMwhrA3EBOPyI"
        }
      ],
      "services": {
        "appinvite_service": {
          "other_platform_oauth_client": []
        }
      }
    }
  ],
  "configuration_version": "1"
}